.coveragerc
.gitignore
.isort.cfg
.pre-commit-config.yaml
.travis.yml
AUTHORS.rst
CHANGELOG.rst
LICENSE.txt
Makefile
README.rst
pyproject.toml
requirements.txt
setup.cfg
setup.py
tox.ini
docs/Makefile
docs/authors.rst
docs/changelog.rst
docs/conf.py
docs/index.rst
docs/license.rst
docs/_static/.gitignore
src/metapack_jupyter/__init__.py
src/metapack_jupyter/appurl.py
src/metapack_jupyter/cli.py
src/metapack_jupyter/convert.py
src/metapack_jupyter/core.py
src/metapack_jupyter/exc.py
src/metapack_jupyter/exec.py
src/metapack_jupyter/exporters.py
src/metapack_jupyter/hugo.py
src/metapack_jupyter/ipython.py
src/metapack_jupyter/magic.py
src/metapack_jupyter/markdown.py
src/metapack_jupyter/metapack.py
src/metapack_jupyter/pandas.py
src/metapack_jupyter/preprocessors.py
src/metapack_jupyter/rowgenerator.py
src/metapack_jupyter/script.py
src/metapack_jupyter/wordpress.py
src/metapack_jupyter.egg-info/PKG-INFO
src/metapack_jupyter.egg-info/SOURCES.txt
src/metapack_jupyter.egg-info/dependency_links.txt
src/metapack_jupyter.egg-info/entry_points.txt
src/metapack_jupyter.egg-info/not-zip-safe
src/metapack_jupyter.egg-info/requires.txt
src/metapack_jupyter.egg-info/top_level.txt
src/metapack_jupyter/templates/__init__.py
src/metapack_jupyter/templates/hide_input_html.tpl
src/metapack_jupyter/templates/hide_input_html_basic.tpl
src/metapack_jupyter/templates/html_wordpress.tpl
src/metapack_jupyter/templates/markdown_hugo.tpl
src/metapack_jupyter/templates/notebook.tplx
tests/conftest.py
tests/test_skeleton.py
tests/travis_install.sh
tests/test/New Notebook Style.ipynb
tests/test/.ipynb_checkpoints/New Notebook Style-checkpoint.ipynb
tests/test/test_data/TestNotebook1.ipynb
tests/test/test_data/.ipynb_checkpoints/TestNotebook1-checkpoint.ipynb