Metadata-Version: 2.1
Name: metapack-jupyter
Version: 0.1.0
Summary: Jupyter extension to Metapack
Home-page: https://github.com/Metatab/metapack-jupyter.git
Author: Eric Busboom
Author-email: eric@civicknowledge.com
License: mit
Platform: any
Classifier: Development Status :: 4 - Beta
Classifier: Programming Language :: Python
Provides-Extra: testing
